dhcp_o82/cli.py
dhcp_o82/o82.py
dhcp_o82-0.1.0.dist-info/entry_points.txt
dhcp_o82-0.1.0.dist-info/LICENSE.txt
dhcp_o82-0.1.0.dist-info/WHEEL
dhcp_o82-0.1.0.dist-info/METADATA
dhcp_o82-0.1.0.dist-info/RECORD
