Metadata-Version: 2.1
Name: dhcp-o82
Version: 0.1.0
Summary: Makes humans working with DHCP Option 82/RelayAgentInfo possible.
Author: Manny Garcia
Author-email: mannygar@cisco.com
Requires-Python: >=3.9,<4.0
Classifier: Programming Language :: Python :: 3
Classifier: Programming Language :: Python :: 3.10
Classifier: Programming Language :: Python :: 3.9
Requires-Dist: click (>=8.1.3,<9.0.0)
Requires-Dist: netaddr (>=0.8.0,<0.9.0)
